[
    {
    "route": "NIS",
    "direction": 0,
    "NextStop": 1,
    "Chi": "歡迎乘搭",
    "ChiLED": "rbxassetid://12223812274",
    "ChiTime": 5,
    "Eng": "WELCOME ONBOARD",
    "EngTime": 5,
    "SoundId": "rbxassetid://",
    "TimePosition": 0,
    "Notification": 0
  },
{
    "route": "SW1",
    "direction": 0,
    "NextStop": 1,
    "Chi": "歡迎乘搭石永探索號",
    "ChiLED": "rbxassetid:/12223812274",
    "ChiTime": 5,
    "Eng": "WELCOME ONBOARD\nSHEK WING EXPLORER",
    "EngTime": 5,
    "SoundId": "rbxassetid://",
    "TimePosition": 0,
    "Notification": 0
  },
  {
    "route": "SW1",
    "direction": 0,
    "NextStop": 2,
    "Chi": "南翔購物中心",
    "ChiLED": "rbxassetid:/12223812274",
    "ChiTime": 5,
    "Eng": "NAM CHEUNG\nSHOPPING CENTRE",
    "EngTime": 5,
    "SoundId": "rbxassetid://",
    "TimePosition": 0,
    "Notification": 1
  },
    {
    "route": "SW1",
    "direction": 0,
    "NextStop": 3,
    "Chi": "石永隧道轉車站",
    "ChiLED": "rbxassetid:/12223812274",
    "ChiTime": 5,
    "Eng": "SHEK WING TUNNEL BBI",
    "EngTime": 5,
    "SoundId": "rbxassetid://",
    "TimePosition": 0,
    "Notification": 2
  },
     {
    "route": "SW1",
    "direction": 0,
    "NextStop": 4,
    "Chi": "背沙澄天匯",
    "ChiLED": "rbxassetid:/12223812274",
    "ChiTime": 5,
    "Eng": "BUI SHA\nVIBRANT AZURE",
    "EngTime": 5,
    "SoundId": "rbxassetid://",
    "TimePosition": 0,
    "Notification": 1
  },
    {
    "route": "SW1",
    "direction": 0,
    "NextStop": 5,
    "Chi": "背沙超級城",
    "ChiLED": "rbxassetid:/12223812274",
    "ChiTime": 5,
    "Eng": "BUI SHA MEGA MALL",
    "EngTime": 5,
    "SoundId": "rbxassetid://",
    "TimePosition": 0,
    "Notification": 1
  },
    {
    "route": "SW1",
    "direction": 0,
    "NextStop": 6,
    "Chi": "雲石道觀景台",
    "ChiLED": "rbxassetid:/12223812274",
    "ChiTime": 5,
    "Eng": "BUI SHA MEGA MALL",
    "EngTime": 5,
    "SoundId": "rbxassetid://",
    "TimePosition": 0,
    "Notification": 2
  },
    {
    "route": "SW1",
    "direction": 0,
    "NextStop": 6,
    "Chi": "雲石道觀景台",
    "ChiLED": "rbxassetid:/12223812274",
    "ChiTime": 5,
    "Eng": "WAN SHEK ROAD\nVIEWING POINT",
    "EngTime": 5,
    "SoundId": "rbxassetid://",
    "TimePosition": 0,
    "Notification": 1
  },
    {
    "route": "SW1",
    "direction": 0,
    "NextStop": 7,
    "Chi": "石永隧道轉車站",
    "ChiLED": "rbxassetid:/12223812274",
    "ChiTime": 5,
    "Eng": "SHEK WING TUNNEL BBI",
    "EngTime": 5,
    "SoundId": "rbxassetid://",
    "TimePosition": 0,
    "Notification": 2
  },
    {
    "route": "SW1",
    "direction": 0,
    "NextStop": 8,
    "Chi": "尚安碼頭",
    "ChiLED": "rbxassetid:/12223812274",
    "ChiTime": 5,
    "Eng": "SHEUNG ON PIER",
    "EngTime": 5,
    "SoundId": "rbxassetid://",
    "TimePosition": 0,
    "Notification": 1
  },
    {
    "route": "SW1",
    "direction": 0,
    "NextStop": 9,
    "Chi": "石永泳灘海邊圍邨",
    "ChiLED": "rbxassetid:/12223812274",
    "ChiTime": 5,
    "Eng": "SHEK WING BEACH\nSEA BEACH VILLAGE ESTATE",
    "EngTime": 5,
    "SoundId": "rbxassetid://",
    "TimePosition": 0,
    "Notification": 1
  },
    {
    "route": "SW1",
    "direction": 0,
    "NextStop": 10,
    "Chi": "石永市中心石永邨",
    "ChiLED": "rbxassetid:/12223812274",
    "ChiTime": 5,
    "Eng": "SHEK WING TOWN CENTRE\nSHEK WING ESTATE B/T",
    "EngTime": 5,
    "SoundId": "rbxassetid://",
    "TimePosition": 0,
    "Notification": 1
  },
{
    "route": "SW1",
    "direction": 0,
    "NextStop": 11,
    "Chi": "巴士總站 多謝乘搭",
    "ChiLED": "rbxassetid://11416972631",
    "ChiTime": 5,
    "Eng": "THANK YOU FOR TRAVELLING\nSHEK WING EXPLORER",
    "EngTime": 5,
    "SoundId": "rbxassetid://",
    "TimePosition": 0,
    "Notification": 0
  }
]
